apitests/__init__.py
apitests/base.py
apitests/helpers.py
apitests/mixins.py
apitests/points.py
apitests/settings.py
apitests/stub.py
apitests/utils.py
apitests/workflow.py
apitests/contrib/__init__.py
apitests/contrib/asserts.py
apitests/contrib/gemini.py
apitests/contrib/logs.py
apitests/generator/__init__.py
apitests/generator/generalizer.py
apitests/generator/stubgen.py
apitests/generator/transformer.py
apitests/serialization/__init__.py
apitests/serialization/arazzo.py
apitests/serialization/visual.py
apitests-0.0.2.dist-info/licenses/LICENSE
apitests-0.0.2.dist-info/METADATA
apitests-0.0.2.dist-info/WHEEL
apitests-0.0.2.dist-info/top_level.txt
apitests-0.0.2.dist-info/RECORD
