Metadata-Version: 2.4
Name: apitests
Version: 0.0.2
Summary: APITESTS: AI-Powered Runtime Test Generator for Microservices
Author-email: Eugene Rabtsau <e.ryabtsev@gmail.com>
Project-URL: Source, https://github.com/ryabtsev/apitests
Classifier: Programming Language :: Python :: 3
Classifier: License :: OSI Approved :: BSD License
Classifier: Operating System :: OS Independent
Requires-Python: >=3.8
License-File: LICENSE
Requires-Dist: requests
Requires-Dist: PyYAML
Requires-Dist: Jinja2
Requires-Dist: parse
Dynamic: license-file
